LICENSE
MANIFEST.in
README.md
setup.py
np_autodiscovery/__init__.py
np_autodiscovery/apps.py
np_autodiscovery/constants.py
np_autodiscovery/filters.py
np_autodiscovery/forms.py
np_autodiscovery/models.py
np_autodiscovery/tables.py
np_autodiscovery/urls.py
np_autodiscovery/views.py
np_autodiscovery/worker.py
np_autodiscovery.egg-info/PKG-INFO
np_autodiscovery.egg-info/SOURCES.txt
np_autodiscovery.egg-info/dependency_links.txt
np_autodiscovery.egg-info/requires.txt
np_autodiscovery.egg-info/top_level.txt
np_autodiscovery/migrations/0001_initial.py
np_autodiscovery/migrations/__init__.py
np_autodiscovery/templates/np_autodiscovery/discoveryrequest.html
np_autodiscovery/templates/np_autodiscovery/discoveryrequest_edit.html
np_autodiscovery/templates/np_autodiscovery/discoveryrequest_list.html